CHANGELOG.rst
LICENSE
berserk/__init__.py
berserk/clients/__init__.py
berserk/clients/account.py
berserk/clients/base.py
berserk/clients/board.py
berserk/clients/bots.py
berserk/clients/broadcasts.py
berserk/clients/bulk_pairings.py
berserk/clients/challenges.py
berserk/clients/external_engine.py
berserk/clients/games.py
berserk/clients/messaging.py
berserk/clients/oauth.py
berserk/clients/opening_explorer.py
berserk/clients/puzzles.py
berserk/clients/relations.py
berserk/clients/simuls.py
berserk/clients/studies.py
berserk/clients/tablebase.py
berserk/clients/teams.py
berserk/clients/tournaments.py
berserk/clients/tv.py
berserk/clients/users.py
berserk/exceptions.py
berserk/formats.py
berserk/models.py
berserk/py.typed
berserk/session.py
berserk/types/__init__.py
berserk/types/account.py
berserk/types/bulk_pairings.py
berserk/types/challenges.py
berserk/types/common.py
berserk/types/opening_explorer.py
berserk/types/puzzles.py
berserk/types/team.py
berserk/types/tournaments.py
berserk/utils.py
berserk-0.13.1.dist-info/LICENSE
berserk-0.13.1.dist-info/METADATA
berserk-0.13.1.dist-info/WHEEL
berserk-0.13.1.dist-info/RECORD
