Metadata-Version: 2.1
Name: berserk
Version: 0.13.1
Summary: Python client for the lichess API
Home-page: https://github.com/lichess-org/berserk
License: GPL-3.0-or-later
Keywords: lichess,chess,api,client
Author: Lichess
Author-email: contact@lichess.org
Requires-Python: >=3.8,<4.0
Classifier: Development Status :: 4 - Beta
Classifier: Intended Audience :: Developers
Classifier: License :: OSI Approved :: GNU General Public License v3 or later (GPLv3+)
Classifier: Natural Language :: English
Classifier: Programming Language :: Python :: 3
Classifier: Programming Language :: Python :: 3.8
Classifier: Programming Language :: Python :: 3.9
Classifier: Programming Language :: Python :: 3.10
Classifier: Programming Language :: Python :: 3.11
Requires-Dist: deprecated (>=1.2.14,<2.0.0)
Requires-Dist: ndjson (>=0.3.1,<0.4.0)
Requires-Dist: python-dateutil (>=2.8.2,<3.0.0)
Requires-Dist: requests (>=2.28.2,<3.0.0)
Requires-Dist: typing-extensions (>=4.7.1,<5.0.0)
Project-URL: Changelog, https://lichess-org.github.io/berserk/changelog.html
Project-URL: Documentation, https://lichess-org.github.io/berserk/
Project-URL: Discord Server, https://discord.gg/lichess
Project-URL: Issue Tracker, https://github.com/lichess-org/berserk/issues
Project-URL: Repository, https://github.com/lichess-org/berserk
